bayesian_gp_cvloss/__init__.py
bayesian_gp_cvloss/optimizer.py
bayesian_gp_cvloss-0.1.5.dist-info/licenses/LICENSE
bayesian_gp_cvloss-0.1.5.dist-info/METADATA
bayesian_gp_cvloss-0.1.5.dist-info/WHEEL
bayesian_gp_cvloss-0.1.5.dist-info/top_level.txt
bayesian_gp_cvloss-0.1.5.dist-info/RECORD
