Metadata-Version: 2.4
Name: bayesian-gp-cvloss
Version: 0.1.5
Summary: A Python package for Gaussian Process Regression with hyperparameter optimization using Hyperopt and cross-validation, focusing on optimizing cross-validated loss.
Home-page: https://github.com/Shifa-Zhong/bayesian-gp-cvloss
Author: Shifa Zhong
Author-email: sfzhong@tongji.edu.cn
Classifier: Development Status :: 3 - Alpha
Classifier: Intended Audience :: Science/Research
Classifier: Intended Audience :: Developers
Classifier: License :: OSI Approved :: MIT License
Classifier: Programming Language :: Python :: 3
Classifier: Programming Language :: Python :: 3.8
Classifier: Programming Language :: Python :: 3.9
Classifier: Programming Language :: Python :: 3.10
Classifier: Operating System :: OS Independent
Classifier: Topic :: Scientific/Engineering :: Artificial Intelligence
Classifier: Topic :: Software Development :: Libraries :: Python Modules
Requires-Python: >=3.8
License-File: LICENSE
Requires-Dist: gpflow>=2.0.0
Requires-Dist: hyperopt>=0.2.0
Requires-Dist: scikit-learn>=0.23.0
Requires-Dist: pandas>=1.0.0
Requires-Dist: numpy>=1.18.0
Dynamic: author
Dynamic: author-email
Dynamic: classifier
Dynamic: description
Dynamic: description-content-type
Dynamic: home-page
Dynamic: license-file
Dynamic: requires-dist
Dynamic: requires-python
Dynamic: summary
